datamug/__init__.py
datamug/hello.py
datamug/mug.py
datamug/reader/__init__.py
datamug/reader/text_reader.py
datamug/utils/__init__.py
datamug/utils/models.py
datamug/utils/test.py
datamug-0.0.23.dist-info/LICENSE.txt
datamug-0.0.23.dist-info/METADATA
datamug-0.0.23.dist-info/WHEEL
datamug-0.0.23.dist-info/top_level.txt
datamug-0.0.23.dist-info/RECORD
