Metadata-Version: 2.1
Name: datamug
Version: 0.0.23
Summary: Python package to generate training data with LLMs for LLMs
Home-page: https://github.com/erfanvaredi/datamug
Author: Erfan Varedi
Author-email: erfanvaredi@gmail.com
Project-URL: Bug Tracker, https://github.com/erfanvaredi/datamug/-/issues
Project-URL: Repository, https://github.com/erfanvaredi/datamug
Classifier: Programming Language :: Python :: 3
Classifier: License :: OSI Approved :: MIT License
Classifier: Operating System :: OS Independent
Requires-Python: >=3.7
License-File: LICENSE.txt
Requires-Dist: langchain ==0.1.11
Requires-Dist: langchainhub ==0.1.15
Requires-Dist: sentence-transformers ==2.5.1
Requires-Dist: langchain-community ==0.0.27
Requires-Dist: python-dotenv ==0.21.0
Requires-Dist: black ==22.10.0
Requires-Dist: openai ==0.28
Requires-Dist: setuptools
